ai_models_gfs/__init__.py
ai_models_gfs/__main__.py
ai_models_gfs/_version.py
ai_models_gfs/checkpoint.py
ai_models_gfs/model.py
ai_models_gfs/stepper.py
ai_models_gfs/inputs/__init__.py
ai_models_gfs/inputs/base.py
ai_models_gfs/inputs/cds.py
ai_models_gfs/inputs/compute.py
ai_models_gfs/inputs/file.py
ai_models_gfs/inputs/gfs.py
ai_models_gfs/inputs/interpolate.py
ai_models_gfs/inputs/mars.py
ai_models_gfs/inputs/opendata.py
ai_models_gfs/inputs/recenter.py
ai_models_gfs/inputs/transform.py
ai_models_gfs/outputs/__init__.py
ai_models_gfs/outputs/grib2nc.py
ai_models_gfs/remote/__init__.py
ai_models_gfs/remote/api.py
ai_models_gfs/remote/config.py
ai_models_gfs/remote/model.py
ai_models_gfs-0.0.21.dist-info/LICENSE
ai_models_gfs-0.0.21.dist-info/METADATA
ai_models_gfs-0.0.21.dist-info/WHEEL
ai_models_gfs-0.0.21.dist-info/entry_points.txt
ai_models_gfs-0.0.21.dist-info/top_level.txt
ai_models_gfs-0.0.21.dist-info/RECORD
