Metadata-Version: 2.2
Name: ai-models-gfs
Version: 0.0.21
Summary: A package to run AI weather models.
Author-email: "European Centre for Medium-Range Weather Forecasts (ECMWF)" <software.support@ecmwf.int>
Maintainer-email: Jacob Radford <jacob.t.radford@gmail.com>
License:                                  Apache License
Project-URL: Homepage, https://github.com/ecmwf-lab/ai-models
Project-URL: Repository, https://github.com/jacob-radford/ai-models-gfs
Project-URL: Issues, https://github.com/jacob-radford/ai-models-gfs/issues
Keywords: tools,ai
Classifier: Development Status :: 4 - Beta
Classifier: Intended Audience :: Developers
Classifier: License :: OSI Approved :: Apache Software License
Classifier: Programming Language :: Python :: 3
Classifier: Programming Language :: Python :: 3.9
Classifier: Programming Language :: Python :: 3.10
Classifier: Programming Language :: Python :: 3.11
Classifier: Programming Language :: Python :: Implementation :: CPython
Classifier: Programming Language :: Python :: Implementation :: PyPy
Classifier: Operating System :: OS Independent
Requires-Python: >=3.9
License-File: LICENSE
Requires-Dist: cdsapi
Requires-Dist: earthkit-data>=0.11.3
Requires-Dist: earthkit-meteo
Requires-Dist: earthkit-regrid
Requires-Dist: eccodes>=2.37
Requires-Dist: ecmwf-api-client
Requires-Dist: ecmwf-opendata
Requires-Dist: entrypoints
Requires-Dist: gputil
Requires-Dist: multiurl
Requires-Dist: numpy<2
Requires-Dist: pyyaml
Requires-Dist: requests
Requires-Dist: tqdm
